urcollectionmanager/api.py
urcollectionmanager/auth.py
urcollectionmanager/database.py
urcollectionmanager/history.py
urcollectionmanager/http.py
urcollectionmanager/mission.py
urcollectionmanager/missions.py
urcollectionmanager/purchase.py
urcollectionmanager-1.1.3.dist-info/LICENSE
urcollectionmanager-1.1.3.dist-info/WHEEL
urcollectionmanager-1.1.3.dist-info/METADATA
urcollectionmanager-1.1.3.dist-info/RECORD
