Metadata-Version: 2.1
Name: urcollectionmanager
Version: 1.1.3
Summary: API for Urban Rivals collection management
Home-page: https://github.com/brentspector/urcollectionmanager
License: MIT
Author: Brent Spector
Author-email: brent.spector@yahoo.com
Requires-Python: >=3.8.0,<4.0.0
Classifier: License :: OSI Approved :: MIT License
Classifier: Programming Language :: Python :: 3
Classifier: Programming Language :: Python :: 3.8
Requires-Dist: bs4 (>=0.0.1,<0.0.2)
Requires-Dist: requests (>=2.23.0,<3.0.0)
Requires-Dist: sqlalchemy (>=1.3.15,<2.0.0)
Project-URL: Repository, https://github.com/brentspector/urcollectionmanager
